backyard/__init__.py
backyard-0.0.1.dist-info/METADATA
backyard-0.0.1.dist-info/WHEEL
backyard-0.0.1.dist-info/licenses/LICENSE
backyard-0.0.1.dist-info/RECORD
