Metadata-Version: 2.4
Name: backyard
Version: 0.0.1
Summary: backyard
Author-email: Hammad Saeed <hvmmad@gmail.com>
License:                                  Apache License
License-File: LICENSE
Requires-Python: >=3.9
